setup.py
support/__init__.py
support/async.py
support/buffered_socket.py
support/cache.py
support/connection_mgr.py
support/context.py
support/crypto.py
support/exceptions.py
support/group.py
support/gurllib2.py
support/http_client.py
support/ll.py
support/log.py
support/redis.py
support/socket_pool.py
support/socklusion.py
support/stomp.py
support.egg-info/PKG-INFO
support.egg-info/SOURCES.txt
support.egg-info/dependency_links.txt
support.egg-info/not-zip-safe
support.egg-info/requires.txt
support.egg-info/top_level.txt
support/meta_service/__init__.py
support/meta_service/codeview.py
support/meta_service/eval_server.py
support/meta_service/meta_service.py
support/meta_service/obj_browser.py
support/meta_service/stats.py